ensae2019tmkw/__init__.py
ensae2019tmkw/main.py
ensae2019tmkw-1.0.dist-info/LICENSE.txt
ensae2019tmkw-1.0.dist-info/METADATA
ensae2019tmkw-1.0.dist-info/WHEEL
ensae2019tmkw-1.0.dist-info/top_level.txt
ensae2019tmkw-1.0.dist-info/RECORD
