Metadata-Version: 2.1
Name: ensae2019tmkw
Version: 1.0
Summary: A package for graphics
Home-page: https://github.com/pypa/sampleproject
Author: KONDO
Author-email: afanboj1@gmail.com
License: UNKNOWN
Platform: UNKNOWN
Classifier: Programming Language :: Python :: 3
Classifier: License :: OSI Approved :: MIT License
Classifier: Operating System :: OS Independent
Requires-Python: >=3.6
